LICENSE
README.md
setup.py
marinate/__init__.py
marinate/marinate.py
marinate/utils.py
marinate.egg-info/PKG-INFO
marinate.egg-info/SOURCES.txt
marinate.egg-info/dependency_links.txt
marinate.egg-info/top_level.txt