Metadata-Version: 2.1
Name: marinate
Version: 1.0.1
Summary: A Python package called marinate
Home-page: https://github.com/shobrook/marinate
Author: shobrook
Author-email: shobrookj@gmail.com
License: MIT
Requires-Python: >=3
License-File: LICENSE
